evenv/__init__.py
evenv/__main__.py
evenv/bundled/python-3.12.8-embedtk-amd64.zip
evenv-1.0.2.dist-info/METADATA
evenv-1.0.2.dist-info/WHEEL
evenv-1.0.2.dist-info/top_level.txt
evenv-1.0.2.dist-info/RECORD
