Metadata-Version: 2.1
Name: evenv
Version: 1.0.2
Summary: Creates virtual embeddable Python environments in one or more target directories.
Home-page: https://github.com/artemdorozhkin/evenv
Author: artemdorozhkin
Author-email: aa.dorozhkin@ya.ru
Classifier: Programming Language :: Python :: 3
Classifier: License :: OSI Approved :: MIT License
Classifier: Operating System :: OS Independent
Requires-Python: >=3.7
